{
  "Pixhawk":
    {
    "COM": "com13"
	},
  "GNSS1":
    {
    "COM": "COM10",
	"baud": 115200,
	"timeout": 1,
	"takt": 0.2,
	"bytesize": null,
	"parity": null,
	"simulation":false
	},
  "GNSS2":
    {
    "COM": "COM11",
	"baud": 115200,
	"timeout": 1,
	"takt": 0.2,
	"bytesize": null,
	"parity": null,
	"simulation":false
	},
  "Echolot":
    {
    "COM": "COM1",
	"baud": 19200,
	"timeout": 1,
	"takt": 0.2,
	"bytesize": null,
	"parity": null,
	"simulation":false
	},
  "Distanz":
    {
    "COM": "COM8",
	"baud": 19200,
	"timeout": 1,
	"takt": 1,
	"bytesize":7,
	"parity":"E",
	"simulation":false
	}
}